[
  {
    "publishingOffice": "大阪管区気象台",
    "reportDatetime": "2021-11-07T17:00:00+09:00",
    "timeSeries": [
      {
        "timeDefines": [
          "2021-11-07T17:00:00+09:00",
          "2021-11-08T00:00:00+09:00",
          "2021-11-09T00:00:00+09:00"
        ],
        "areas": [
          {
            "area": {
              "name": "大阪府",
              "code": "270000"
            },
            "weatherCodes": [
              "211",
              "212",
              "313"
            ],
            "weathers": [
              "くもり　夜　晴れ",
              "くもり　夜遅く　雨　所により　雷　を伴う","雨　
後　くもり"],"winds":["北東の風　海上　では　北東の風　やや強く","北東の風　海上　では　北東の風　やや強く","西の風　やや強く"],"waves":["１メートル","０．５メートル　後　１メートル","１メートル　後　０．５メートル"]}]},{"timeDefines":["2021-11-07T18: 00: 00+09: 00","2021-11-08T00: 00: 00+09: 00","2021-11-08T06: 00: 00+09: 00","2021-11-08T12: 00: 00+09: 00","2021-11-08T18: 00: 00+09: 00"],"areas":[{"area":{"name":"大阪府","code":"270000"},"pops":["0","10","10","20","60"]}]},{"timeDefines":["2021-11-08T00: 00: 00+09: 00","2021-11-08T09: 00: 00+09: 00"],"areas":[{"area":{"name":"大阪","code":"62078"},"temps":["16","22"]}]}]},{"publishingOffice":"大阪管区気象台","reportDatetime":"2021-11-07T17: 00: 00+09: 00","timeSeries":[{"timeDefines":["2021-11-08T00: 00: 00+09: 00","2021-11-09T00: 00: 00+09: 00","2021-11-10T00: 00: 00+09: 00","2021-11-11T00: 00: 00+09: 00","2021-11-12T00: 00: 00+09: 00","2021-11-13T00: 00: 00+09: 00","2021-11-14T00: 00: 00+09: 00"],"areas":[{"area":{"name":"大阪府","code":"270000"},"weatherCodes":["212","313","101","101","101","101","101"],"pops":["","80","10","10","10","10","10"],"reliabilities":["","","A","A","A","A","A"]}]},{"timeDefines":["2021-11-08T00: 00: 00+09: 00","2021-11-09T00: 00: 00+09: 00","2021-11-10T00: 00: 00+09: 00","2021-11-11T00: 00: 00+09: 00","2021-11-12T00: 00: 00+09: 00","2021-11-13T00: 00: 00+09: 00","2021-11-14T00: 00: 00+09: 00"],"areas":[{"area":{"name":"大阪","code":"62078"},"tempsMin":["","14","12","12","11","8","7"],"tempsMinUpper":["","15","13","13","12","10","12"],"tempsMinLower":["","12","10","9","9","6","6"],"tempsMax":["","19","17","17","16","17","19"],"tempsMaxUpper":["","21","19","19","19","20","20"],"tempsMaxLower":["","18","15","15","15","15","14"]}]}],"tempAverage":{"areas":[{"area":{"name":"大阪","code":"62078"},"min":"11.2","max":"18.8"}]},"precipAverage":{"areas":[{"area":{"name":"大阪","code":"62078"},"min":"5.3","max":"19.9"}]}}]
